abstractions/__init__.py
abstractions/async_abstractions.py
abstractions/iterables.py
abstractions/storage.py
abstractions/yaml.py
abstractions-0.6.4.dist-info/WHEEL
abstractions-0.6.4.dist-info/METADATA
abstractions-0.6.4.dist-info/RECORD
