Metadata-Version: 2.3
Name: abstractions
Version: 0.6.4
Summary: Abstractions for Python programming
Author: Arjun Guha
Author-email: Arjun Guha <a.guha@northeastern.edu>
Requires-Python: >=3.11
